glossy/__init__.py
glossy/decorated.py
glossy/decorators.py
glossy/inspect.py
glossy/test.py
glossy-0.0.3.dist-info/LICENSE
glossy-0.0.3.dist-info/METADATA
glossy-0.0.3.dist-info/WHEEL
glossy-0.0.3.dist-info/top_level.txt
glossy-0.0.3.dist-info/RECORD
